partitioned.py
partitioned-0.1.4.dist-info/METADATA
partitioned-0.1.4.dist-info/WHEEL
partitioned-0.1.4.dist-info/entry_points.txt
partitioned-0.1.4.dist-info/top_level.txt
partitioned-0.1.4.dist-info/RECORD
